unsplashpy.py
unsplashpy-0.0.2.dist-info/METADATA
unsplashpy-0.0.2.dist-info/RECORD
unsplashpy-0.0.2.dist-info/WHEEL
unsplashpy-0.0.2.dist-info/top_level.txt
