Metadata-Version: 2.1
Name: unsplashpy
Version: 0.0.2
Summary: A Unsplash client without the need for an api key
Home-page: https://github.com/sauldom102/unsplashpy
Author: Saul Dominguez
Author-email: saulydominguez@gmail.com
License: UNKNOWN
Platform: UNKNOWN
Classifier: Programming Language :: Python :: 3
Classifier: License :: OSI Approved :: MIT License
Classifier: Operating System :: OS Independent
